busho/__init__.py
busho/busho.py
busho-1.1.dist-info/LICENSE
busho-1.1.dist-info/METADATA
busho-1.1.dist-info/WHEEL
busho-1.1.dist-info/top_level.txt
busho-1.1.dist-info/RECORD
