Metadata-Version: 2.1
Name: busho
Version: 1.1
Summary: Multi-host deployment.
Home-page: https://github.com/Czw96/propor
Author: Czw_96
Author-email: 459749926@qq.com
License: UNKNOWN
Platform: UNKNOWN
Classifier: Programming Language :: Python :: 3
Classifier: License :: OSI Approved :: MIT License
Classifier: Operating System :: OS Independent
Requires-Dist: paramiko
Requires-Dist: eloope
